{"created_at": "Fri Dec 08 01:44:20 +0000 2017", "id": 938947318312775680, "id_str": "938947318312775680", "text": "RT @Pele: Congratulations to @Cristiano on winning this year's Ballon d'Or. I would love to have played on the same side as y\u2026 ", "source": "<a href=\"http://twitter.com/download/android\" rel=\"nofollow\">Twitter for Android</a>", "truncated": false, "in_reply_to_status_id": null, "in_reply_to_status_id_str": null, "in_reply_to_user_id": null, "in_reply_to_user_id_str": null, "in_reply_to_screen_name": null, "user": {"id": 713691726418952194, "id_str": "713691726418952194", "name": "\u0410\u0445\u043c\u0435\u0434 \u0410\u0442\u0435\u0444", "screen_name": "Ahmed3atef72", "location": null, "url": null, "description": "\u200f\u200f\u200f\u200f\u200f\u200f\u200f\u200f\u200f\u200f\u200f\u200f\u0631\u064a\u0627\u0644 \u0645\u062f\u0631\u064a\u062f \u0644\u064a\u0633 \u0645\u062c\u0631\u062f \u0646\u0627\u062f\u0649 \u0628\u0644 \u062d\u064a\u0627\u0647\u060c\u0627\u0630\u0627 \u0645\u062f\u0631\u064a\u062f \u0628\u062e\u064a\u0631 \u0641\u0627\u0646\u0627 \u0643\u0630\u0627\u0644\u0643\u060c \u0627\u0628\u062d\u062b \u0639\u0646 \u0627\u0644\u062b\u0627\u0644\u062b\u0629 \u0639\u0634\u0631 \u064a\u0627 \u0645\u0646 \u062a\u0628\u062d\u062b \u0639\u0646 \u0646\u0635\u0641 \u0645 \u0627\u0628\u062d\u062b \u0639\u0646\u0647, 12 \u0644\u0642\u0628 \u0641 \u0627\u0644\u0645\u062a\u062d\u0641.Man United Is My Heave", "translator_type": "none", "protected": false, "verified": false, "followers_count": 430, "friends_count": 108, "listed_count": 8, "favourites_count": 613, "statuses_count": 7056, "created_at": "Sat Mar 26 11:39:02 +0000 2016", "utc_offset": -28800, "time_zone": "Pacific Time (US & Canada)", "geo_enabled": false, "lang": "en", "contributors_enabled": false, "is_translator": false, "profile_background_color": "000000", "profile_background_image_url": "http://abs.twimg.com/images/themes/theme1/bg.png", "profile_background_image_url_https": "https://abs.twimg.com/images/themes/theme1/bg.png", "profile_background_tile": false, "profile_link_color": "E81C4F", "profile_sidebar_border_color": "000000", "profile_sidebar_fill_color": "000000", "profile_text_color": "000000", "profile_use_background_image": false, "profile_image_url": "http://pbs.twimg.com/profile_images/938852445341569025/uLM1lQfS_normal.jpg", "profile_image_url_https": "https://pbs.twimg.com/profile_images/938852445341569025/uLM1lQfS_normal.jpg", "profile_banner_url": "https://pbs.twimg.com/profile_banners/713691726418952194/1507544190", "default_profile": false, "default_profile_image": false, "following": null, "follow_request_sent": null, "notifications": null}, "geo": null, "coordinates": null, "place": null, "contributors": null, "retweeted_status": {"created_at": "Thu Dec 07 19:06:42 +0000 2017", "id": 938847251052597249, "id_str": "938847251052597249", "text": "Congratulations to @Cristiano on winning this year's Ballon d'Or. I would love to have played on the same side as y\u2026 https://t.co/tMHXztVNnW", "source": "<a href=\"http://twitter.com\" rel=\"nofollow\">Twitter Web Client</a>", "truncated": true, "in_reply_to_status_id": null, "in_reply_to_status_id_str": null, "in_reply_to_user_id": null, "in_reply_to_user_id_str": null, "in_reply_to_screen_name": null, "user": {"id": 480782173, "id_str": "480782173", "name": "Pel\u00e9", "screen_name": "Pele", "location": null, "url": "http://pele10.com", "description": "http://Facebook.com/Pele", "translator_type": "regular", "protected": false, "verified": true, "followers_count": 2465770, "friends_count": 83, "listed_count": 3909, "favourites_count": 84, "statuses_count": 2168, "created_at": "Wed Feb 01 22:08:19 +0000 2012", "utc_offset": -18000, "time_zone": "Eastern Time (US & Canada)", "geo_enabled": false, "lang": "en", "contributors_enabled": false, "is_translator": false, "profile_background_color": "000000", "profile_background_image_url": "http://pbs.twimg.com/profile_background_images/506903727/1.jpeg", "profile_background_image_url_https": "https://pbs.twimg.com/profile_background_images/506903727/1.jpeg", "profile_background_tile": false, "profile_link_color": "0084B4", "profile_sidebar_border_color": "C0DEED", "profile_sidebar_fill_color": "DDEEF6", "profile_text_color": "333333", "profile_use_background_image": true, "profile_image_url": "http://pbs.twimg.com/profile_images/2699904552/28b81ad1d4cf42d4c1bb1c8bac58fe02_normal.jpeg", "profile_image_url_https": "https://pbs.twimg.com/profile_images/2699904552/28b81ad1d4cf42d4c1bb1c8bac58fe02_normal.jpeg", "profile_banner_url": "https://pbs.twimg.com/profile_banners/480782173/1349822791", "default_profile": false, "default_profile_image": false, "following": null, "follow_request_sent": null, "notifications": null}, "geo": null, "coordinates": null, "place": null, "contributors": null, "is_quote_status": false, "extended_tweet": {"full_text": "Congratulations to @Cristiano on winning this year's Ballon d'Or. I would love to have played on the same side as you! // Parab\u00e9ns ao @Cristiano por conquistar o Ballon d'Or este ano. Eu adoraria ter tido a chance de jogar ao seu lado! #BallondOr", "display_text_range": [0, 246], "entities": {"hashtags": [{"text": "BallondOr", "indices": [236, 246]}], "urls": [], "user_mentions": [{"screen_name": "Cristiano", "name": "Cristiano Ronaldo", "id": 155659213, "id_str": "155659213", "indices": [19, 29]}, {"screen_name": "Cristiano", "name": "Cristiano Ronaldo", "id": 155659213, "id_str": "155659213", "indices": [134, 144]}], "symbols": []}}, "quote_count": 193, "reply_count": 93, "retweet_count": 4805, "favorite_count": 6444, "entities": {"hashtags": [], "urls": [{"url": "https://t.co/tMHXztVNnW", "expanded_url": "https://twitter.com/i/web/status/938847251052597249", "display_url": "twitter.com/i/web/status/9\u2026", "indices": [117, 140]}], "user_mentions": [{"screen_name": "Cristiano", "name": "Cristiano Ronaldo", "id": 155659213, "id_str": "155659213", "indices": [19, 29]}], "symbols": []}, "favorited": false, "retweeted": false, "filter_level": "low", "lang": "en"}, "is_quote_status": false, "quote_count": 0, "reply_count": 0, "retweet_count": 0, "favorite_count": 0, "entities": {"hashtags": [], "urls": [], "user_mentions": [{"screen_name": "Pele", "name": "Pel\u00e9", "id": 480782173, "id_str": "480782173", "indices": [3, 8]}, {"screen_name": "Cristiano", "name": "Cristiano Ronaldo", "id": 155659213, "id_str": "155659213", "indices": [29, 39]}], "symbols": []}, "favorited": false, "retweeted": false, "filter_level": "low", "lang": "en", "timestamp_ms": "1512697460140"}