{"created_at": "Fri Dec 08 01:46:16 +0000 2017", "id": 938947808102514688, "id_str": "938947808102514688", "text": "RT @nickcoppack: Reading a lot of #BallondOr opinions that are basically: \u201cI\u2019m sick of watching two of the greatest ever footballers\u2026 ", "source": "<a href=\"http://twitter.com/download/android\" rel=\"nofollow\">Twitter for Android</a>", "truncated": false, "in_reply_to_status_id": null, "in_reply_to_status_id_str": null, "in_reply_to_user_id": null, "in_reply_to_user_id_str": null, "in_reply_to_screen_name": null, "user": {"id": 289276141, "id_str": "289276141", "name": "Tushar Kamath", "screen_name": "GlorifiedUnited", "location": "Parts Unknown", "url": null, "description": "JOS\u00c9 M\u00c1RIO DOS SANTOS MOURINHO FELIX", "translator_type": "none", "protected": false, "verified": false, "followers_count": 1355, "friends_count": 582, "listed_count": 13, "favourites_count": 24840, "statuses_count": 33177, "created_at": "Thu Apr 28 10:40:32 +0000 2011", "utc_offset": 19800, "time_zone": "Mumbai", "geo_enabled": false, "lang": "en", "contributors_enabled": false, "is_translator": false, "profile_background_color": "FFF04D", "profile_background_image_url": "http://pbs.twimg.com/profile_background_images/378800000043965467/2a8cb2e3326f795ebf3aa3745d95409b.jpeg", "profile_background_image_url_https": "https://pbs.twimg.com/profile_background_images/378800000043965467/2a8cb2e3326f795ebf3aa3745d95409b.jpeg", "profile_background_tile": true, "profile_link_color": "0099CC", "profile_sidebar_border_color": "FFFFFF", "profile_sidebar_fill_color": "F6FFD1", "profile_text_color": "333333", "profile_use_background_image": true, "profile_image_url": "http://pbs.twimg.com/profile_images/867633502988238848/bcr4ozKH_normal.jpg", "profile_image_url_https": "https://pbs.twimg.com/profile_images/867633502988238848/bcr4ozKH_normal.jpg", "profile_banner_url": "https://pbs.twimg.com/profile_banners/289276141/1418276284", "default_profile": false, "default_profile_image": false, "following": null, "follow_request_sent": null, "notifications": null}, "geo": null, "coordinates": null, "place": null, "contributors": null, "retweeted_status": {"created_at": "Fri Dec 08 00:54:53 +0000 2017", "id": 938934874169380864, "id_str": "938934874169380864", "text": "Reading a lot of #BallondOr opinions that are basically: \u201cI\u2019m sick of watching two of the greatest ever footballers\u2026 https://t.co/G6avu19EeC", "display_text_range": [0, 140], "source": "<a href=\"http://twitter.com/download/iphone\" rel=\"nofollow\">Twitter for iPhone</a>", "truncated": true, "in_reply_to_status_id": null, "in_reply_to_status_id_str": null, "in_reply_to_user_id": null, "in_reply_to_user_id_str": null, "in_reply_to_screen_name": null, "user": {"id": 151870675, "id_str": "151870675", "name": "Nick Coppack", "screen_name": "nickcoppack", "location": "Manchester", "url": null, "description": "Social Media @BBCSport. Ex-@ManUtd.", "translator_type": "none", "protected": false, "verified": false, "followers_count": 62649, "friends_count": 299, "listed_count": 1162, "favourites_count": 414, "statuses_count": 27427, "created_at": "Fri Jun 04 13:18:03 +0000 2010", "utc_offset": 0, "time_zone": "London", "geo_enabled": true, "lang": "en", "contributors_enabled": false, "is_translator": false, "profile_background_color": "000000", "profile_background_image_url": "http://pbs.twimg.com/profile_background_images/195657056/x860ff630f6d24f0f93b909d614419c4.png", "profile_background_image_url_https": "https://pbs.twimg.com/profile_background_images/195657056/x860ff630f6d24f0f93b909d614419c4.png", "profile_background_tile": true, "profile_link_color": "AC0909", "profile_sidebar_border_color": "F47D77", "profile_sidebar_fill_color": "FFFFFF", "profile_text_color": "0C3E53", "profile_use_background_image": true, "profile_image_url": "http://pbs.twimg.com/profile_images/843239533995053056/-0KO_PKh_normal.jpg", "profile_image_url_https": "https://pbs.twimg.com/profile_images/843239533995053056/-0KO_PKh_normal.jpg", "profile_banner_url": "https://pbs.twimg.com/profile_banners/151870675/1490138509", "default_profile": false, "default_profile_image": false, "following": null, "follow_request_sent": null, "notifications": null}, "geo": null, "coordinates": null, "place": null, "contributors": null, "is_quote_status": false, "extended_tweet": {"full_text": "Reading a lot of #BallondOr opinions that are basically: \u201cI\u2019m sick of watching two of the greatest ever footballers play every week. Their dominance is boring.\u201d\n\nAre you kidding? We are blessed. We are not worthy. Enjoy it! https://t.co/giRx3fxkGq", "display_text_range": [0, 223], "entities": {"hashtags": [{"text": "BallondOr", "indices": [17, 27]}], "urls": [], "user_mentions": [], "symbols": [], "media": [{"id": 938934848458252288, "id_str": "938934848458252288", "indices": [224, 247], "media_url": "http://pbs.twimg.com/tweet_video_thumb/DQfERR2W4AAFh7H.jpg", "media_url_https": "https://pbs.twimg.com/tweet_video_thumb/DQfERR2W4AAFh7H.jpg", "url": "https://t.co/giRx3fxkGq", "display_url": "pic.twitter.com/giRx3fxkGq", "expanded_url": "https://twitter.com/nickcoppack/status/938934874169380864/photo/1", "type": "animated_gif", "sizes": {"medium": {"w": 480, "h": 286, "resize": "fit"}, "small": {"w": 480, "h": 286, "resize": "fit"}, "thumb": {"w": 150, "h": 150, "resize": "crop"}, "large": {"w": 480, "h": 286, "resize": "fit"}}, "video_info": {"aspect_ratio": [240, 143], "variants": [{"bitrate": 0, "content_type": "video/mp4", "url": "https://video.twimg.com/tweet_video/DQfERR2W4AAFh7H.mp4"}]}}]}, "extended_entities": {"media": [{"id": 938934848458252288, "id_str": "938934848458252288", "indices": [224, 247], "media_url": "http://pbs.twimg.com/tweet_video_thumb/DQfERR2W4AAFh7H.jpg", "media_url_https": "https://pbs.twimg.com/tweet_video_thumb/DQfERR2W4AAFh7H.jpg", "url": "https://t.co/giRx3fxkGq", "display_url": "pic.twitter.com/giRx3fxkGq", "expanded_url": "https://twitter.com/nickcoppack/status/938934874169380864/photo/1", "type": "animated_gif", "sizes": {"medium": {"w": 480, "h": 286, "resize": "fit"}, "small": {"w": 480, "h": 286, "resize": "fit"}, "thumb": {"w": 150, "h": 150, "resize": "crop"}, "large": {"w": 480, "h": 286, "resize": "fit"}}, "video_info": {"aspect_ratio": [240, 143], "variants": [{"bitrate": 0, "content_type": "video/mp4", "url": "https://video.twimg.com/tweet_video/DQfERR2W4AAFh7H.mp4"}]}}]}}, "quote_count": 0, "reply_count": 1, "retweet_count": 4, "favorite_count": 14, "entities": {"hashtags": [{"text": "BallondOr", "indices": [17, 27]}], "urls": [{"url": "https://t.co/G6avu19EeC", "expanded_url": "https://twitter.com/i/web/status/938934874169380864", "display_url": "twitter.com/i/web/status/9\u2026", "indices": [117, 140]}], "user_mentions": [], "symbols": []}, "favorited": false, "retweeted": false, "possibly_sensitive": false, "filter_level": "low", "lang": "en"}, "is_quote_status": false, "quote_count": 0, "reply_count": 0, "retweet_count": 0, "favorite_count": 0, "entities": {"hashtags": [{"text": "BallondOr", "indices": [34, 44]}], "urls": [], "user_mentions": [{"screen_name": "nickcoppack", "name": "Nick Coppack", "id": 151870675, "id_str": "151870675", "indices": [3, 15]}], "symbols": []}, "favorited": false, "retweeted": false, "filter_level": "low", "lang": "en", "timestamp_ms": "1512697576915"}