{"created_at": "Fri Dec 08 01:53:58 +0000 2017", "id": 938949744084291585, "id_str": "938949744084291585", "text": "RT @reema_zara: Epic \ud83d\ude0d\ud83d\udc4c\n#BallondOr #CR7 https://t.co/FQxtSyurps", "source": "<a href=\"http://twitter.com/download/android\" rel=\"nofollow\">Twitter for Android</a>", "truncated": false, "in_reply_to_status_id": null, "in_reply_to_status_id_str": null, "in_reply_to_user_id": null, "in_reply_to_user_id_str": null, "in_reply_to_screen_name": null, "user": {"id": 327168072, "id_str": "327168072", "name": "Edwin Pinzon", "screen_name": "edwinpin07", "location": "Granada, Colombia", "url": null, "description": "Fan\u00e1tico del buen f\u00fatbol, Seguidor del mejor equipo del mundo Real Madrid\u26bdSr4\u202292:48\u2764", "translator_type": "none", "protected": false, "verified": false, "followers_count": 434, "friends_count": 300, "listed_count": 4, "favourites_count": 5454, "statuses_count": 5091, "created_at": "Fri Jul 01 03:18:00 +0000 2011", "utc_offset": -18000, "time_zone": "Bogota", "geo_enabled": true, "lang": "es", "contributors_enabled": false, "is_translator": false, "profile_background_color": "C0DEED", "profile_background_image_url": "http://abs.twimg.com/images/themes/theme1/bg.png", "profile_background_image_url_https": "https://abs.twimg.com/images/themes/theme1/bg.png", "profile_background_tile": false, "profile_link_color": "1DA1F2", "profile_sidebar_border_color": "C0DEED", "profile_sidebar_fill_color": "DDEEF6", "profile_text_color": "333333", "profile_use_background_image": true, "profile_image_url": "http://pbs.twimg.com/profile_images/937558837678297088/R0fINZYG_normal.jpg", "profile_image_url_https": "https://pbs.twimg.com/profile_images/937558837678297088/R0fINZYG_normal.jpg", "profile_banner_url": "https://pbs.twimg.com/profile_banners/327168072/1511816365", "default_profile": true, "default_profile_image": false, "following": null, "follow_request_sent": null, "notifications": null}, "geo": null, "coordinates": null, "place": null, "contributors": null, "retweeted_status": {"created_at": "Thu Dec 07 19:38:28 +0000 2017", "id": 938855245530071040, "id_str": "938855245530071040", "text": "Epic \ud83d\ude0d\ud83d\udc4c\n#BallondOr #CR7 https://t.co/FQxtSyurps", "display_text_range": [0, 23], "source": "<a href=\"http://twitter.com/download/android\" rel=\"nofollow\">Twitter for Android</a>", "truncated": false, "in_reply_to_status_id": null, "in_reply_to_status_id_str": null, "in_reply_to_user_id": null, "in_reply_to_user_id_str": null, "in_reply_to_screen_name": null, "user": {"id": 313122342, "id_str": "313122342", "name": "R\u025b\u025b\u028da Za\u0280a", "screen_name": "reema_zara", "location": null, "url": null, "description": "Fan Girl Of Ilayathalapathy Vijay | Samantha Crazen | Rahmaniac | Genelia |  DQ | \u2764 Bunny | CR7 | Hala Madrid | Madridista | Foodie | Nature Lover |", "translator_type": "none", "protected": false, "verified": false, "followers_count": 2326, "friends_count": 201, "listed_count": 5, "favourites_count": 12261, "statuses_count": 12769, "created_at": "Wed Jun 08 05:25:12 +0000 2011", "utc_offset": 19800, "time_zone": "Sri Jayawardenepura", "geo_enabled": false, "lang": "en", "contributors_enabled": false, "is_translator": false, "profile_background_color": "E81C4F", "profile_background_image_url": "http://pbs.twimg.com/profile_background_images/660187739317362688/StuPiOtt.jpg", "profile_background_image_url_https": "https://pbs.twimg.com/profile_background_images/660187739317362688/StuPiOtt.jpg", "profile_background_tile": false, "profile_link_color": "E81C4F", "profile_sidebar_border_color": "000000", "profile_sidebar_fill_color": "000000", "profile_text_color": "000000", "profile_use_background_image": true, "profile_image_url": "http://pbs.twimg.com/profile_images/938861050807517184/dAHvfoGv_normal.jpg", "profile_image_url_https": "https://pbs.twimg.com/profile_images/938861050807517184/dAHvfoGv_normal.jpg", "profile_banner_url": "https://pbs.twimg.com/profile_banners/313122342/1507282619", "default_profile": false, "default_profile_image": false, "following": null, "follow_request_sent": null, "notifications": null}, "geo": null, "coordinates": null, "place": null, "contributors": null, "is_quote_status": false, "quote_count": 6, "reply_count": 0, "retweet_count": 121, "favorite_count": 300, "entities": {"hashtags": [{"text": "BallondOr", "indices": [8, 18]}, {"text": "CR7", "indices": [19, 23]}], "urls": [], "user_mentions": [], "symbols": [], "media": [{"id": 938855233861455877, "id_str": "938855233861455877", "indices": [24, 47], "media_url": "http://pbs.twimg.com/media/DQd73GXUEAUcnl3.jpg", "media_url_https": "https://pbs.twimg.com/media/DQd73GXUEAUcnl3.jpg", "url": "https://t.co/FQxtSyurps", "display_url": "pic.twitter.com/FQxtSyurps", "expanded_url": "https://twitter.com/reema_zara/status/938855245530071040/photo/1", "type": "photo", "sizes": {"small": {"w": 680, "h": 492, "resize": "fit"}, "thumb": {"w": 150, "h": 150, "resize": "crop"}, "medium": {"w": 1200, "h": 868, "resize": "fit"}, "large": {"w": 1242, "h": 898, "resize": "fit"}}}]}, "extended_entities": {"media": [{"id": 938855233861455877, "id_str": "938855233861455877", "indices": [24, 47], "media_url": "http://pbs.twimg.com/media/DQd73GXUEAUcnl3.jpg", "media_url_https": "https://pbs.twimg.com/media/DQd73GXUEAUcnl3.jpg", "url": "https://t.co/FQxtSyurps", "display_url": "pic.twitter.com/FQxtSyurps", "expanded_url": "https://twitter.com/reema_zara/status/938855245530071040/photo/1", "type": "photo", "sizes": {"small": {"w": 680, "h": 492, "resize": "fit"}, "thumb": {"w": 150, "h": 150, "resize": "crop"}, "medium": {"w": 1200, "h": 868, "resize": "fit"}, "large": {"w": 1242, "h": 898, "resize": "fit"}}}]}, "favorited": false, "retweeted": false, "possibly_sensitive": false, "filter_level": "low", "lang": "en"}, "is_quote_status": false, "quote_count": 0, "reply_count": 0, "retweet_count": 0, "favorite_count": 0, "entities": {"hashtags": [{"text": "BallondOr", "indices": [24, 34]}, {"text": "CR7", "indices": [35, 39]}], "urls": [], "user_mentions": [{"screen_name": "reema_zara", "name": "R\u025b\u025b\u028da Za\u0280a", "id": 313122342, "id_str": "313122342", "indices": [3, 14]}], "symbols": [], "media": [{"id": 938855233861455877, "id_str": "938855233861455877", "indices": [40, 63], "media_url": "http://pbs.twimg.com/media/DQd73GXUEAUcnl3.jpg", "media_url_https": "https://pbs.twimg.com/media/DQd73GXUEAUcnl3.jpg", "url": "https://t.co/FQxtSyurps", "display_url": "pic.twitter.com/FQxtSyurps", "expanded_url": "https://twitter.com/reema_zara/status/938855245530071040/photo/1", "type": "photo", "sizes": {"small": {"w": 680, "h": 492, "resize": "fit"}, "thumb": {"w": 150, "h": 150, "resize": "crop"}, "medium": {"w": 1200, "h": 868, "resize": "fit"}, "large": {"w": 1242, "h": 898, "resize": "fit"}}, "source_status_id": 938855245530071040, "source_status_id_str": "938855245530071040", "source_user_id": 313122342, "source_user_id_str": "313122342"}]}, "extended_entities": {"media": [{"id": 938855233861455877, "id_str": "938855233861455877", "indices": [40, 63], "media_url": "http://pbs.twimg.com/media/DQd73GXUEAUcnl3.jpg", "media_url_https": "https://pbs.twimg.com/media/DQd73GXUEAUcnl3.jpg", "url": "https://t.co/FQxtSyurps", "display_url": "pic.twitter.com/FQxtSyurps", "expanded_url": "https://twitter.com/reema_zara/status/938855245530071040/photo/1", "type": "photo", "sizes": {"small": {"w": 680, "h": 492, "resize": "fit"}, "thumb": {"w": 150, "h": 150, "resize": "crop"}, "medium": {"w": 1200, "h": 868, "resize": "fit"}, "large": {"w": 1242, "h": 898, "resize": "fit"}}, "source_status_id": 938855245530071040, "source_status_id_str": "938855245530071040", "source_user_id": 313122342, "source_user_id_str": "313122342"}]}, "favorited": false, "retweeted": false, "possibly_sensitive": false, "filter_level": "low", "lang": "en", "timestamp_ms": "1512698038489"}