{"created_at": "Fri Dec 08 01:48:15 +0000 2017", "id": 938948306725679106, "id_str": "938948306725679106", "text": "C'est vrai que la 25\u00e8me place pour Benzema elle est abus\u00e9 ! #BallondOr", "source": "<a href=\"http://twitter.com/download/android\" rel=\"nofollow\">Twitter for Android</a>", "truncated": false, "in_reply_to_status_id": null, "in_reply_to_status_id_str": null, "in_reply_to_user_id": null, "in_reply_to_user_id_str": null, "in_reply_to_screen_name": null, "user": {"id": 2912499177, "id_str": "2912499177", "name": "Il Pendolino", "screen_name": "valentin_dcre", "location": "France", "url": null, "description": "\ud83d\udcaa\ud83c\udf55\ud83c\udfcb\ufe0f\u200d\u2642\ufe0f\ud83c\uddeb\ud83c\uddf7\u26bd\ufe0f", "translator_type": "none", "protected": false, "verified": false, "followers_count": 185, "friends_count": 209, "listed_count": 5, "favourites_count": 8108, "statuses_count": 7865, "created_at": "Tue Dec 09 10:49:54 +0000 2014", "utc_offset": null, "time_zone": null, "geo_enabled": true, "lang": "fr", "contributors_enabled": false, "is_translator": false, "profile_background_color": "C0DEED", "profile_background_image_url": "http://abs.twimg.com/images/themes/theme1/bg.png", "profile_background_image_url_https": "https://abs.twimg.com/images/themes/theme1/bg.png", "profile_background_tile": false, "profile_link_color": "1DA1F2", "profile_sidebar_border_color": "C0DEED", "profile_sidebar_fill_color": "DDEEF6", "profile_text_color": "333333", "profile_use_background_image": true, "profile_image_url": "http://pbs.twimg.com/profile_images/924078283771334657/RotNwWdr_normal.jpg", "profile_image_url_https": "https://pbs.twimg.com/profile_images/924078283771334657/RotNwWdr_normal.jpg", "profile_banner_url": "https://pbs.twimg.com/profile_banners/2912499177/1502547451", "default_profile": true, "default_profile_image": false, "following": null, "follow_request_sent": null, "notifications": null}, "geo": null, "coordinates": null, "place": {"id": "09a302fb9d9b51df", "url": "https://api.twitter.com/1.1/geo/id/09a302fb9d9b51df.json", "place_type": "city", "name": "Pommer\u00e9val", "full_name": "Pommer\u00e9val, France", "country_code": "FR", "country": "France", "bounding_box": {"type": "Polygon", "coordinates": [[[1.272195, 49.715525], [1.272195, 49.758121], [1.331262, 49.758121], [1.331262, 49.715525]]]}, "attributes": {}}, "contributors": null, "is_quote_status": false, "quote_count": 0, "reply_count": 0, "retweet_count": 0, "favorite_count": 0, "entities": {"hashtags": [{"text": "BallondOr", "indices": [60, 70]}], "urls": [], "user_mentions": [], "symbols": []}, "favorited": false, "retweeted": false, "filter_level": "low", "lang": "fr", "timestamp_ms": "1512697695796"}