{"created_at": "Fri Dec 08 01:50:09 +0000 2017", "id": 938948782733119488, "id_str": "938948782733119488", "text": "RT @roberdiez10: Si Ramos es el sexto mejor jugador del mundo yo ya no entiendo nada.... https://t.co/y5AQhB7L25", "source": "<a href=\"http://twitter.com/download/android\" rel=\"nofollow\">Twitter for Android</a>", "truncated": false, "in_reply_to_status_id": null, "in_reply_to_status_id_str": null, "in_reply_to_user_id": null, "in_reply_to_user_id_str": null, "in_reply_to_screen_name": null, "user": {"id": 605556216, "id_str": "605556216", "name": "Senra", "screen_name": "sergio_senra", "location": "Noia ", "url": null, "description": "Hay sue\u00f1os que s\u00f3lo se alcanzan con los pies\nCentral exjugador del CF Noia y actual del SD Compostela , Deportivista de coraz\u00f3n no trates de entenderlo.", "translator_type": "none", "protected": false, "verified": false, "followers_count": 398, "friends_count": 365, "listed_count": 4, "favourites_count": 14299, "statuses_count": 12330, "created_at": "Mon Jun 11 14:44:02 +0000 2012", "utc_offset": null, "time_zone": null, "geo_enabled": false, "lang": "es", "contributors_enabled": false, "is_translator": false, "profile_background_color": "C0DEED", "profile_background_image_url": "http://abs.twimg.com/images/themes/theme1/bg.png", "profile_background_image_url_https": "https://abs.twimg.com/images/themes/theme1/bg.png", "profile_background_tile": false, "profile_link_color": "1DA1F2", "profile_sidebar_border_color": "C0DEED", "profile_sidebar_fill_color": "DDEEF6", "profile_text_color": "333333", "profile_use_background_image": true, "profile_image_url": "http://pbs.twimg.com/profile_images/868080275355570177/pGAVYhVv_normal.jpg", "profile_image_url_https": "https://pbs.twimg.com/profile_images/868080275355570177/pGAVYhVv_normal.jpg", "profile_banner_url": "https://pbs.twimg.com/profile_banners/605556216/1449447191", "default_profile": true, "default_profile_image": false, "following": null, "follow_request_sent": null, "notifications": null}, "geo": null, "coordinates": null, "place": null, "contributors": null, "retweeted_status": {"created_at": "Thu Dec 07 18:31:49 +0000 2017", "id": 938838474177830913, "id_str": "938838474177830913", "text": "Si Ramos es el sexto mejor jugador del mundo yo ya no entiendo nada.... https://t.co/y5AQhB7L25", "display_text_range": [0, 71], "source": "<a href=\"http://twitter.com/download/android\" rel=\"nofollow\">Twitter for Android</a>", "truncated": false, "in_reply_to_status_id": null, "in_reply_to_status_id_str": null, "in_reply_to_user_id": null, "in_reply_to_user_id_str": null, "in_reply_to_screen_name": null, "user": {"id": 2199700791, "id_str": "2199700791", "name": "deabru10", "screen_name": "roberdiez10", "location": null, "url": null, "description": null, "translator_type": "none", "protected": false, "verified": false, "followers_count": 506, "friends_count": 1184, "listed_count": 10, "favourites_count": 6816, "statuses_count": 9952, "created_at": "Thu Nov 28 20:35:22 +0000 2013", "utc_offset": null, "time_zone": null, "geo_enabled": false, "lang": "es", "contributors_enabled": false, "is_translator": false, "profile_background_color": "C0DEED", "profile_background_image_url": "http://abs.twimg.com/images/themes/theme1/bg.png", "profile_background_image_url_https": "https://abs.twimg.com/images/themes/theme1/bg.png", "profile_background_tile": false, "profile_link_color": "1DA1F2", "profile_sidebar_border_color": "C0DEED", "profile_sidebar_fill_color": "DDEEF6", "profile_text_color": "333333", "profile_use_background_image": true, "profile_image_url": "http://pbs.twimg.com/profile_images/581421048006074368/qdQI-BS3_normal.jpg", "profile_image_url_https": "https://pbs.twimg.com/profile_images/581421048006074368/qdQI-BS3_normal.jpg", "default_profile": true, "default_profile_image": false, "following": null, "follow_request_sent": null, "notifications": null}, "geo": null, "coordinates": null, "place": null, "contributors": null, "quoted_status_id": 938838072149663750, "quoted_status_id_str": "938838072149663750", "quoted_status": {"created_at": "Thu Dec 07 18:30:13 +0000 2017", "id": 938838072149663750, "id_str": "938838072149663750", "text": "10. Kane\n9. Lewandowski\n8. Kant\u00e9\n7. Mbapp\u00e9\n6. Ramos\n\n#BallondOr", "source": "<a href=\"http://twitter.com\" rel=\"nofollow\">Twitter Web Client</a>", "truncated": false, "in_reply_to_status_id": 938829217873178624, "in_reply_to_status_id_str": "938829217873178624", "in_reply_to_user_id": 860478832192741376, "in_reply_to_user_id_str": "860478832192741376", "in_reply_to_screen_name": "ManuLorenzo_2", "user": {"id": 860478832192741376, "id_str": "860478832192741376", "name": "Manu Lorenzo", "screen_name": "ManuLorenzo_2", "location": "Noia, Espa\u00f1a", "url": "http://somosoutsiders.blogspot.com.es", "description": "En esta cuenta se habla de deporte. Y mucho. Tambi\u00e9n me pod\u00e9is encontrar en @somos_outsiders, mi nuevo blog \ud83d\ude09\ud83d\ude07 Sigo queriendo recuperar @ManuLorenzo_ \ud83e\udd23", "translator_type": "none", "protected": false, "verified": false, "followers_count": 145, "friends_count": 1426, "listed_count": 0, "favourites_count": 1741, "statuses_count": 13383, "created_at": "Fri May 05 12:58:35 +0000 2017", "utc_offset": null, "time_zone": null, "geo_enabled": false, "lang": "es", "contributors_enabled": false, "is_translator": false, "profile_background_color": "F5F8FA", "profile_background_image_url": "", "profile_background_image_url_https": "", "profile_background_tile": false, "profile_link_color": "1DA1F2", "profile_sidebar_border_color": "C0DEED", "profile_sidebar_fill_color": "DDEEF6", "profile_text_color": "333333", "profile_use_background_image": true, "profile_image_url": "http://pbs.twimg.com/profile_images/905934828243230721/4rItIFMm_normal.jpg", "profile_image_url_https": "https://pbs.twimg.com/profile_images/905934828243230721/4rItIFMm_normal.jpg", "profile_banner_url": "https://pbs.twimg.com/profile_banners/860478832192741376/1502148789", "default_profile": true, "default_profile_image": false, "following": null, "follow_request_sent": null, "notifications": null}, "geo": null, "coordinates": null, "place": null, "contributors": null, "is_quote_status": false, "quote_count": 3, "reply_count": 1, "retweet_count": 0, "favorite_count": 0, "entities": {"hashtags": [{"text": "BallondOr", "indices": [53, 63]}], "urls": [], "user_mentions": [], "symbols": []}, "favorited": false, "retweeted": false, "filter_level": "low", "lang": "und"}, "is_quote_status": true, "quote_count": 0, "reply_count": 1, "retweet_count": 1, "favorite_count": 5, "entities": {"hashtags": [], "urls": [{"url": "https://t.co/y5AQhB7L25", "expanded_url": "https://twitter.com/ManuLorenzo_2/status/938838072149663750", "display_url": "twitter.com/ManuLorenzo_2/\u2026", "indices": [72, 95]}], "user_mentions": [], "symbols": []}, "favorited": false, "retweeted": false, "possibly_sensitive": false, "filter_level": "low", "lang": "es"}, "quoted_status_id": 938838072149663750, "quoted_status_id_str": "938838072149663750", "quoted_status": {"created_at": "Thu Dec 07 18:30:13 +0000 2017", "id": 938838072149663750, "id_str": "938838072149663750", "text": "10. Kane\n9. Lewandowski\n8. Kant\u00e9\n7. Mbapp\u00e9\n6. Ramos\n\n#BallondOr", "source": "<a href=\"http://twitter.com\" rel=\"nofollow\">Twitter Web Client</a>", "truncated": false, "in_reply_to_status_id": 938829217873178624, "in_reply_to_status_id_str": "938829217873178624", "in_reply_to_user_id": 860478832192741376, "in_reply_to_user_id_str": "860478832192741376", "in_reply_to_screen_name": "ManuLorenzo_2", "user": {"id": 860478832192741376, "id_str": "860478832192741376", "name": "Manu Lorenzo", "screen_name": "ManuLorenzo_2", "location": "Noia, Espa\u00f1a", "url": "http://somosoutsiders.blogspot.com.es", "description": "En esta cuenta se habla de deporte. Y mucho. Tambi\u00e9n me pod\u00e9is encontrar en @somos_outsiders, mi nuevo blog \ud83d\ude09\ud83d\ude07 Sigo queriendo recuperar @ManuLorenzo_ \ud83e\udd23", "translator_type": "none", "protected": false, "verified": false, "followers_count": 145, "friends_count": 1426, "listed_count": 0, "favourites_count": 1741, "statuses_count": 13383, "created_at": "Fri May 05 12:58:35 +0000 2017", "utc_offset": null, "time_zone": null, "geo_enabled": false, "lang": "es", "contributors_enabled": false, "is_translator": false, "profile_background_color": "F5F8FA", "profile_background_image_url": "", "profile_background_image_url_https": "", "profile_background_tile": false, "profile_link_color": "1DA1F2", "profile_sidebar_border_color": "C0DEED", "profile_sidebar_fill_color": "DDEEF6", "profile_text_color": "333333", "profile_use_background_image": true, "profile_image_url": "http://pbs.twimg.com/profile_images/905934828243230721/4rItIFMm_normal.jpg", "profile_image_url_https": "https://pbs.twimg.com/profile_images/905934828243230721/4rItIFMm_normal.jpg", "profile_banner_url": "https://pbs.twimg.com/profile_banners/860478832192741376/1502148789", "default_profile": true, "default_profile_image": false, "following": null, "follow_request_sent": null, "notifications": null}, "geo": null, "coordinates": null, "place": null, "contributors": null, "is_quote_status": false, "quote_count": 3, "reply_count": 1, "retweet_count": 0, "favorite_count": 0, "entities": {"hashtags": [{"text": "BallondOr", "indices": [53, 63]}], "urls": [], "user_mentions": [], "symbols": []}, "favorited": false, "retweeted": false, "filter_level": "low", "lang": "und"}, "is_quote_status": true, "quote_count": 0, "reply_count": 0, "retweet_count": 0, "favorite_count": 0, "entities": {"hashtags": [], "urls": [{"url": "https://t.co/y5AQhB7L25", "expanded_url": "https://twitter.com/ManuLorenzo_2/status/938838072149663750", "display_url": "twitter.com/ManuLorenzo_2/\u2026", "indices": [89, 112]}], "user_mentions": [{"screen_name": "roberdiez10", "name": "deabru10", "id": 2199700791, "id_str": "2199700791", "indices": [3, 15]}], "symbols": []}, "favorited": false, "retweeted": false, "possibly_sensitive": false, "filter_level": "low", "lang": "es", "timestamp_ms": "1512697809285"}