{"created_at": "Fri Dec 08 01:52:09 +0000 2017", "id": 938949287941165056, "id_str": "938949287941165056", "text": "#bbcqt #BallondOr #bbcqt #UKCityofCulture2021 #Riverdale #Jerusalem #ImACelebrity #CamilaWeAreYourRealFriends https://t.co/vSe5NXSGNC", "display_text_range": [0, 109], "source": "<a href=\"http://twitter.com/download/iphone\" rel=\"nofollow\">Twitter for iPhone</a>", "truncated": false, "in_reply_to_status_id": null, "in_reply_to_status_id_str": null, "in_reply_to_user_id": null, "in_reply_to_user_id_str": null, "in_reply_to_screen_name": null, "user": {"id": 938933066189430785, "id_str": "938933066189430785", "name": "Gemgemgem", "screen_name": "Gemgemgem3", "location": null, "url": null, "description": null, "translator_type": "none", "protected": false, "verified": false, "followers_count": 0, "friends_count": 49, "listed_count": 0, "favourites_count": 1, "statuses_count": 50, "created_at": "Fri Dec 08 00:47:42 +0000 2017", "utc_offset": null, "time_zone": null, "geo_enabled": false, "lang": "en", "contributors_enabled": false, "is_translator": false, "profile_background_color": "F5F8FA", "profile_background_image_url": "", "profile_background_image_url_https": "", "profile_background_tile": false, "profile_link_color": "1DA1F2", "profile_sidebar_border_color": "C0DEED", "profile_sidebar_fill_color": "DDEEF6", "profile_text_color": "333333", "profile_use_background_image": true, "profile_image_url": "http://abs.twimg.com/sticky/default_profile_images/default_profile_normal.png", "profile_image_url_https": "https://abs.twimg.com/sticky/default_profile_images/default_profile_normal.png", "default_profile": true, "default_profile_image": false, "following": null, "follow_request_sent": null, "notifications": null}, "geo": null, "coordinates": null, "place": null, "contributors": null, "quoted_status_id": 938887016305037312, "quoted_status_id_str": "938887016305037312", "quoted_status": {"created_at": "Thu Dec 07 21:44:43 +0000 2017", "id": 938887016305037312, "id_str": "938887016305037312", "text": "This years #ImACeleb has proved: \n- bullying can happen at any age to anyone \n- anxiety/depression can affect anyon\u2026 https://t.co/2T8Tq56Yja", "source": "<a href=\"http://twitter.com/download/iphone\" rel=\"nofollow\">Twitter for iPhone</a>", "truncated": true, "in_reply_to_status_id": null, "in_reply_to_status_id_str": null, "in_reply_to_user_id": null, "in_reply_to_user_id_str": null, "in_reply_to_screen_name": null, "user": {"id": 876890087329587201, "id_str": "876890087329587201", "name": "Jade", "screen_name": "MissJadeW", "location": "Lincoln/Peterborough", "url": "http://www.missjadew.co.uk", "description": "Hey! 23 \ud83c\udf38 food lover, TV junkie & lifestyle blogger xo", "translator_type": "none", "protected": false, "verified": false, "followers_count": 4991, "friends_count": 4066, "listed_count": 7, "favourites_count": 1758, "statuses_count": 2204, "created_at": "Mon Jun 19 19:51:03 +0000 2017", "utc_offset": null, "time_zone": null, "geo_enabled": false, "lang": "en", "contributors_enabled": false, "is_translator": false, "profile_background_color": "000000", "profile_background_image_url": "http://abs.twimg.com/images/themes/theme1/bg.png", "profile_background_image_url_https": "https://abs.twimg.com/images/themes/theme1/bg.png", "profile_background_tile": false, "profile_link_color": "F58EA8", "profile_sidebar_border_color": "000000", "profile_sidebar_fill_color": "000000", "profile_text_color": "000000", "profile_use_background_image": false, "profile_image_url": "http://pbs.twimg.com/profile_images/937021143931858944/-qVdBNZh_normal.jpg", "profile_image_url_https": "https://pbs.twimg.com/profile_images/937021143931858944/-qVdBNZh_normal.jpg", "profile_banner_url": "https://pbs.twimg.com/profile_banners/876890087329587201/1497902013", "default_profile": false, "default_profile_image": false, "following": null, "follow_request_sent": null, "notifications": null}, "geo": null, "coordinates": null, "place": null, "contributors": null, "is_quote_status": false, "extended_tweet": {"full_text": "This years #ImACeleb has proved: \n- bullying can happen at any age to anyone \n- anxiety/depression can affect anyone and people still won\u2019t get it\n- someone from a reality show may get paid less but has a heart of gold", "display_text_range": [0, 218], "entities": {"hashtags": [{"text": "ImACeleb", "indices": [11, 20]}], "urls": [], "user_mentions": [], "symbols": []}}, "quote_count": 115, "reply_count": 16, "retweet_count": 446, "favorite_count": 1703, "entities": {"hashtags": [{"text": "ImACeleb", "indices": [11, 20]}], "urls": [{"url": "https://t.co/2T8Tq56Yja", "expanded_url": "https://twitter.com/i/web/status/938887016305037312", "display_url": "twitter.com/i/web/status/9\u2026", "indices": [117, 140]}], "user_mentions": [], "symbols": []}, "favorited": false, "retweeted": false, "filter_level": "low", "lang": "en"}, "is_quote_status": true, "quote_count": 0, "reply_count": 0, "retweet_count": 0, "favorite_count": 0, "entities": {"hashtags": [{"text": "bbcqt", "indices": [0, 6]}, {"text": "BallondOr", "indices": [7, 17]}, {"text": "bbcqt", "indices": [18, 24]}, {"text": "UKCityofCulture2021", "indices": [25, 45]}, {"text": "Riverdale", "indices": [46, 56]}, {"text": "Jerusalem", "indices": [57, 67]}, {"text": "ImACelebrity", "indices": [68, 81]}, {"text": "CamilaWeAreYourRealFriends", "indices": [82, 109]}], "urls": [{"url": "https://t.co/vSe5NXSGNC", "expanded_url": "https://twitter.com/missjadew/status/938887016305037312", "display_url": "twitter.com/missjadew/stat\u2026", "indices": [110, 133]}], "user_mentions": [], "symbols": []}, "favorited": false, "retweeted": false, "possibly_sensitive": false, "filter_level": "low", "lang": "und", "timestamp_ms": "1512697929736"}