{"created_at": "Fri Dec 08 01:12:54 +0000 2017", "id": 938939408002244609, "id_str": "938939408002244609", "text": "RT @Cover_Shadow: ...and now - 5 Ballon d'Ors later - I finally realized that I don't have to be able to do that. https://t.co/5KjAozs9wO", "source": "<a href=\"http://twitterrific.com\" rel=\"nofollow\">Twitterrific</a>", "truncated": false, "in_reply_to_status_id": null, "in_reply_to_status_id_str": null, "in_reply_to_user_id": null, "in_reply_to_user_id_str": null, "in_reply_to_screen_name": null, "user": {"id": 66208013, "id_str": "66208013", "name": "Luis Espina", "screen_name": "luisespina_v", "location": null, "url": "http://vsco.co/luisespina", "description": "\u201cNo pregunto para no enredar, y entre menos sepa, mejor.\u201d", "translator_type": "none", "protected": false, "verified": false, "followers_count": 166, "friends_count": 471, "listed_count": 9, "favourites_count": 2533, "statuses_count": 24526, "created_at": "Sun Aug 16 22:27:22 +0000 2009", "utc_offset": -14400, "time_zone": "Caracas", "geo_enabled": false, "lang": "en", "contributors_enabled": false, "is_translator": false, "profile_background_color": "131516", "profile_background_image_url": "http://abs.twimg.com/images/themes/theme14/bg.gif", "profile_background_image_url_https": "https://abs.twimg.com/images/themes/theme14/bg.gif", "profile_background_tile": true, "profile_link_color": "009999", "profile_sidebar_border_color": "EEEEEE", "profile_sidebar_fill_color": "EFEFEF", "profile_text_color": "333333", "profile_use_background_image": true, "profile_image_url": "http://pbs.twimg.com/profile_images/921992489908817920/ONNf4SeI_normal.jpg", "profile_image_url_https": "https://pbs.twimg.com/profile_images/921992489908817920/ONNf4SeI_normal.jpg", "profile_banner_url": "https://pbs.twimg.com/profile_banners/66208013/1508655117", "default_profile": false, "default_profile_image": false, "following": null, "follow_request_sent": null, "notifications": null}, "geo": null, "coordinates": null, "place": null, "contributors": null, "retweeted_status": {"created_at": "Thu Dec 07 20:23:44 +0000 2017", "id": 938866637381472264, "id_str": "938866637381472264", "text": "...and now - 5 Ballon d'Ors later - I finally realized that I don't have to be able to do that. https://t.co/5KjAozs9wO", "display_text_range": [0, 95], "source": "<a href=\"http://twitter.com/download/android\" rel=\"nofollow\">Twitter for Android</a>", "truncated": false, "in_reply_to_status_id": null, "in_reply_to_status_id_str": null, "in_reply_to_user_id": null, "in_reply_to_user_id_str": null, "in_reply_to_screen_name": null, "user": {"id": 2228524625, "id_str": "2228524625", "name": "Cover_Shadow", "screen_name": "Cover_Shadow", "location": "Wien", "url": null, "description": "Economics Student | 23 | Real Madrid | Rapid Wien | Dortmund | \u00d8degod", "translator_type": "none", "protected": false, "verified": false, "followers_count": 940, "friends_count": 1267, "listed_count": 0, "favourites_count": 9159, "statuses_count": 21217, "created_at": "Mon Dec 16 12:28:44 +0000 2013", "utc_offset": 3600, "time_zone": "Vienna", "geo_enabled": false, "lang": "de", "contributors_enabled": false, "is_translator": false, "profile_background_color": "000000", "profile_background_image_url": "http://pbs.twimg.com/profile_background_images/704652996664123392/pDg21Nxw.jpg", "profile_background_image_url_https": "https://pbs.twimg.com/profile_background_images/704652996664123392/pDg21Nxw.jpg", "profile_background_tile": false, "profile_link_color": "1B95E0", "profile_sidebar_border_color": "000000", "profile_sidebar_fill_color": "000000", "profile_text_color": "000000", "profile_use_background_image": true, "profile_image_url": "http://pbs.twimg.com/profile_images/875675438336684033/IyghsfoQ_normal.jpg", "profile_image_url_https": "https://pbs.twimg.com/profile_images/875675438336684033/IyghsfoQ_normal.jpg", "profile_banner_url": "https://pbs.twimg.com/profile_banners/2228524625/1479070031", "default_profile": false, "default_profile_image": false, "following": null, "follow_request_sent": null, "notifications": null}, "geo": null, "coordinates": null, "place": null, "contributors": null, "quoted_status_id": 938865193886633985, "quoted_status_id_str": "938865193886633985", "quoted_status": {"created_at": "Thu Dec 07 20:18:00 +0000 2017", "id": 938865193886633985, "id_str": "938865193886633985", "text": "Cristiano: \"I did not expect to win a #BallondOr &amp; now I have 5. When I was 14-16yrs old I realised I had something\u2026 https://t.co/j3EMAVHphm", "display_text_range": [0, 140], "source": "<a href=\"https://about.twitter.com/products/tweetdeck\" rel=\"nofollow\">TweetDeck</a>", "truncated": true, "in_reply_to_status_id": 938859826486095872, "in_reply_to_status_id_str": "938859826486095872", "in_reply_to_user_id": 2464485409, "in_reply_to_user_id_str": "2464485409", "in_reply_to_screen_name": "UltraSuristic_", "user": {"id": 2464485409, "id_str": "2464485409", "name": "M\u2022A\u2022J", "screen_name": "UltraSuristic_", "location": null, "url": null, "description": "Juan G\u00f3mez Gonz\u00e1lez a.k.a JUANITO: If I weren't a player, I'd be an Ultra Sur! -- (back-up @Ultra_Suristic)", "translator_type": "none", "protected": false, "verified": false, "followers_count": 25181, "friends_count": 3884, "listed_count": 396, "favourites_count": 7502, "statuses_count": 30458, "created_at": "Sat Apr 26 11:05:46 +0000 2014", "utc_offset": -28800, "time_zone": "Pacific Time (US & Canada)", "geo_enabled": false, "lang": "en", "contributors_enabled": false, "is_translator": false, "profile_background_color": "131516", "profile_background_image_url": "http://abs.twimg.com/images/themes/theme14/bg.gif", "profile_background_image_url_https": "https://abs.twimg.com/images/themes/theme14/bg.gif", "profile_background_tile": true, "profile_link_color": "009999", "profile_sidebar_border_color": "EEEEEE", "profile_sidebar_fill_color": "EFEFEF", "profile_text_color": "333333", "profile_use_background_image": true, "profile_image_url": "http://pbs.twimg.com/profile_images/707309459001974784/AKw8e3xk_normal.jpg", "profile_image_url_https": "https://pbs.twimg.com/profile_images/707309459001974784/AKw8e3xk_normal.jpg", "profile_banner_url": "https://pbs.twimg.com/profile_banners/2464485409/1490899309", "default_profile": false, "default_profile_image": false, "following": null, "follow_request_sent": null, "notifications": null}, "geo": null, "coordinates": null, "place": null, "contributors": null, "is_quote_status": false, "extended_tweet": {"full_text": "Cristiano: \"I did not expect to win a #BallondOr &amp; now I have 5. When I was 14-16yrs old I realised I had something different than the other kids. Ferguson taught me to be professional, I was very talented but I did not know how to make decisions. When to pass or make plays.\" https://t.co/KbdJULKnOM", "display_text_range": [0, 280], "entities": {"hashtags": [{"text": "BallondOr", "indices": [38, 48]}], "urls": [], "user_mentions": [], "symbols": [], "media": [{"id": 938865181689548800, "id_str": "938865181689548800", "indices": [281, 304], "media_url": "http://pbs.twimg.com/media/DQeE6I6WkAAI-Wz.jpg", "media_url_https": "https://pbs.twimg.com/media/DQeE6I6WkAAI-Wz.jpg", "url": "https://t.co/KbdJULKnOM", "display_url": "pic.twitter.com/KbdJULKnOM", "expanded_url": "https://twitter.com/UltraSuristic_/status/938865193886633985/photo/1", "type": "photo", "sizes": {"medium": {"w": 861, "h": 617, "resize": "fit"}, "thumb": {"w": 150, "h": 150, "resize": "crop"}, "small": {"w": 680, "h": 487, "resize": "fit"}, "large": {"w": 861, "h": 617, "resize": "fit"}}}]}, "extended_entities": {"media": [{"id": 938865181689548800, "id_str": "938865181689548800", "indices": [281, 304], "media_url": "http://pbs.twimg.com/media/DQeE6I6WkAAI-Wz.jpg", "media_url_https": "https://pbs.twimg.com/media/DQeE6I6WkAAI-Wz.jpg", "url": "https://t.co/KbdJULKnOM", "display_url": "pic.twitter.com/KbdJULKnOM", "expanded_url": "https://twitter.com/UltraSuristic_/status/938865193886633985/photo/1", "type": "photo", "sizes": {"medium": {"w": 861, "h": 617, "resize": "fit"}, "thumb": {"w": 150, "h": 150, "resize": "crop"}, "small": {"w": 680, "h": 487, "resize": "fit"}, "large": {"w": 861, "h": 617, "resize": "fit"}}}]}}, "quote_count": 4, "reply_count": 1, "retweet_count": 51, "favorite_count": 124, "entities": {"hashtags": [{"text": "BallondOr", "indices": [38, 48]}], "urls": [{"url": "https://t.co/j3EMAVHphm", "expanded_url": "https://twitter.com/i/web/status/938865193886633985", "display_url": "twitter.com/i/web/status/9\u2026", "indices": [121, 144]}], "user_mentions": [], "symbols": []}, "favorited": false, "retweeted": false, "possibly_sensitive": false, "filter_level": "low", "lang": "en"}, "is_quote_status": true, "quote_count": 0, "reply_count": 1, "retweet_count": 2, "favorite_count": 14, "entities": {"hashtags": [], "urls": [{"url": "https://t.co/5KjAozs9wO", "expanded_url": "https://twitter.com/UltraSuristic_/status/938865193886633985", "display_url": "twitter.com/UltraSuristic_\u2026", "indices": [96, 119]}], "user_mentions": [], "symbols": []}, "favorited": false, "retweeted": false, "possibly_sensitive": false, "filter_level": "low", "lang": "en"}, "quoted_status_id": 938865193886633985, "quoted_status_id_str": "938865193886633985", "quoted_status": {"created_at": "Thu Dec 07 20:18:00 +0000 2017", "id": 938865193886633985, "id_str": "938865193886633985", "text": "Cristiano: \"I did not expect to win a #BallondOr &amp; now I have 5. When I was 14-16yrs old I realised I had something\u2026 https://t.co/j3EMAVHphm", "display_text_range": [0, 140], "source": "<a href=\"https://about.twitter.com/products/tweetdeck\" rel=\"nofollow\">TweetDeck</a>", "truncated": true, "in_reply_to_status_id": 938859826486095872, "in_reply_to_status_id_str": "938859826486095872", "in_reply_to_user_id": 2464485409, "in_reply_to_user_id_str": "2464485409", "in_reply_to_screen_name": "UltraSuristic_", "user": {"id": 2464485409, "id_str": "2464485409", "name": "M\u2022A\u2022J", "screen_name": "UltraSuristic_", "location": null, "url": null, "description": "Juan G\u00f3mez Gonz\u00e1lez a.k.a JUANITO: If I weren't a player, I'd be an Ultra Sur! -- (back-up @Ultra_Suristic)", "translator_type": "none", "protected": false, "verified": false, "followers_count": 25181, "friends_count": 3884, "listed_count": 396, "favourites_count": 7502, "statuses_count": 30458, "created_at": "Sat Apr 26 11:05:46 +0000 2014", "utc_offset": -28800, "time_zone": "Pacific Time (US & Canada)", "geo_enabled": false, "lang": "en", "contributors_enabled": false, "is_translator": false, "profile_background_color": "131516", "profile_background_image_url": "http://abs.twimg.com/images/themes/theme14/bg.gif", "profile_background_image_url_https": "https://abs.twimg.com/images/themes/theme14/bg.gif", "profile_background_tile": true, "profile_link_color": "009999", "profile_sidebar_border_color": "EEEEEE", "profile_sidebar_fill_color": "EFEFEF", "profile_text_color": "333333", "profile_use_background_image": true, "profile_image_url": "http://pbs.twimg.com/profile_images/707309459001974784/AKw8e3xk_normal.jpg", "profile_image_url_https": "https://pbs.twimg.com/profile_images/707309459001974784/AKw8e3xk_normal.jpg", "profile_banner_url": "https://pbs.twimg.com/profile_banners/2464485409/1490899309", "default_profile": false, "default_profile_image": false, "following": null, "follow_request_sent": null, "notifications": null}, "geo": null, "coordinates": null, "place": null, "contributors": null, "is_quote_status": false, "extended_tweet": {"full_text": "Cristiano: \"I did not expect to win a #BallondOr &amp; now I have 5. When I was 14-16yrs old I realised I had something different than the other kids. Ferguson taught me to be professional, I was very talented but I did not know how to make decisions. When to pass or make plays.\" https://t.co/KbdJULKnOM", "display_text_range": [0, 280], "entities": {"hashtags": [{"text": "BallondOr", "indices": [38, 48]}], "urls": [], "user_mentions": [], "symbols": [], "media": [{"id": 938865181689548800, "id_str": "938865181689548800", "indices": [281, 304], "media_url": "http://pbs.twimg.com/media/DQeE6I6WkAAI-Wz.jpg", "media_url_https": "https://pbs.twimg.com/media/DQeE6I6WkAAI-Wz.jpg", "url": "https://t.co/KbdJULKnOM", "display_url": "pic.twitter.com/KbdJULKnOM", "expanded_url": "https://twitter.com/UltraSuristic_/status/938865193886633985/photo/1", "type": "photo", "sizes": {"medium": {"w": 861, "h": 617, "resize": "fit"}, "thumb": {"w": 150, "h": 150, "resize": "crop"}, "small": {"w": 680, "h": 487, "resize": "fit"}, "large": {"w": 861, "h": 617, "resize": "fit"}}}]}, "extended_entities": {"media": [{"id": 938865181689548800, "id_str": "938865181689548800", "indices": [281, 304], "media_url": "http://pbs.twimg.com/media/DQeE6I6WkAAI-Wz.jpg", "media_url_https": "https://pbs.twimg.com/media/DQeE6I6WkAAI-Wz.jpg", "url": "https://t.co/KbdJULKnOM", "display_url": "pic.twitter.com/KbdJULKnOM", "expanded_url": "https://twitter.com/UltraSuristic_/status/938865193886633985/photo/1", "type": "photo", "sizes": {"medium": {"w": 861, "h": 617, "resize": "fit"}, "thumb": {"w": 150, "h": 150, "resize": "crop"}, "small": {"w": 680, "h": 487, "resize": "fit"}, "large": {"w": 861, "h": 617, "resize": "fit"}}}]}}, "quote_count": 4, "reply_count": 1, "retweet_count": 51, "favorite_count": 124, "entities": {"hashtags": [{"text": "BallondOr", "indices": [38, 48]}], "urls": [{"url": "https://t.co/j3EMAVHphm", "expanded_url": "https://twitter.com/i/web/status/938865193886633985", "display_url": "twitter.com/i/web/status/9\u2026", "indices": [121, 144]}], "user_mentions": [], "symbols": []}, "favorited": false, "retweeted": false, "possibly_sensitive": false, "filter_level": "low", "lang": "en"}, "is_quote_status": true, "quote_count": 0, "reply_count": 0, "retweet_count": 2, "favorite_count": 0, "entities": {"hashtags": [], "urls": [{"url": "https://t.co/5KjAozs9wO", "expanded_url": "https://twitter.com/UltraSuristic_/status/938865193886633985", "display_url": "twitter.com/UltraSuristic_\u2026", "indices": [114, 137]}], "user_mentions": [{"screen_name": "Cover_Shadow", "name": "Cover_Shadow", "id": 2228524625, "id_str": "2228524625", "indices": [3, 16]}], "symbols": []}, "favorited": false, "retweeted": false, "possibly_sensitive": false, "filter_level": "low", "lang": "en", "timestamp_ms": "1512695574175"}