{"created_at": "Fri Dec 08 01:56:15 +0000 2017", "id": 938950319530299393, "id_str": "938950319530299393", "text": "Lol this my #Jam \ud83d\udd25 \ud83d\udd25 \nDJ sha just dey play am for my Hostel \n#Mellanby #UI \n#myhallweek\n#BallondOr no worry\u2026 https://t.co/XCnHNJRVvX", "display_text_range": [0, 140], "source": "<a href=\"http://twitter.com/download/android\" rel=\"nofollow\">Twitter for Android</a>", "truncated": true, "in_reply_to_status_id": null, "in_reply_to_status_id_str": null, "in_reply_to_user_id": null, "in_reply_to_user_id_str": null, "in_reply_to_screen_name": null, "user": {"id": 714915952111067137, "id_str": "714915952111067137", "name": "Georgy", "screen_name": "Armaniiarc", "location": "Nigeria ", "url": null, "description": "Artist, Sociologist, humanist, realist, and a Christian you get to know more as you tag along", "translator_type": "none", "protected": false, "verified": false, "followers_count": 35, "friends_count": 166, "listed_count": 0, "favourites_count": 113, "statuses_count": 235, "created_at": "Tue Mar 29 20:43:40 +0000 2016", "utc_offset": null, "time_zone": null, "geo_enabled": false, "lang": "en", "contributors_enabled": false, "is_translator": false, "profile_background_color": "F5F8FA", "profile_background_image_url": "", "profile_background_image_url_https": "", "profile_background_tile": false, "profile_link_color": "1DA1F2", "profile_sidebar_border_color": "C0DEED", "profile_sidebar_fill_color": "DDEEF6", "profile_text_color": "333333", "profile_use_background_image": true, "profile_image_url": "http://pbs.twimg.com/profile_images/937648955562786816/id2aUY43_normal.jpg", "profile_image_url_https": "https://pbs.twimg.com/profile_images/937648955562786816/id2aUY43_normal.jpg", "default_profile": true, "default_profile_image": false, "following": null, "follow_request_sent": null, "notifications": null}, "geo": null, "coordinates": null, "place": null, "contributors": null, "is_quote_status": false, "extended_tweet": {"full_text": "Lol this my #Jam \ud83d\udd25 \ud83d\udd25 \nDJ sha just dey play am for my Hostel \n#Mellanby #UI \n#myhallweek\n#BallondOr no worry @DONJAZZY go dey the remix \u270c\u270c https://t.co/YHbv1vXSFx", "display_text_range": [0, 137], "entities": {"hashtags": [{"text": "Jam", "indices": [12, 16]}, {"text": "Mellanby", "indices": [61, 70]}, {"text": "UI", "indices": [71, 74]}, {"text": "myhallweek", "indices": [76, 87]}, {"text": "BallondOr", "indices": [88, 98]}], "urls": [], "user_mentions": [{"screen_name": "DONJAZZY", "name": "ITS DONJAZZY AGAIN\ud83d\ude09", "id": 53817066, "id_str": "53817066", "indices": [108, 117]}], "symbols": [], "media": [{"id": 938942917338640385, "id_str": "938942917338640385", "indices": [138, 161], "media_url": "http://pbs.twimg.com/ext_tw_video_thumb/938942917338640385/pu/img/IcidzuFgcfqt8ciT.jpg", "media_url_https": "https://pbs.twimg.com/ext_tw_video_thumb/938942917338640385/pu/img/IcidzuFgcfqt8ciT.jpg", "url": "https://t.co/YHbv1vXSFx", "display_url": "pic.twitter.com/YHbv1vXSFx", "expanded_url": "https://twitter.com/Armaniiarc/status/938950319530299393/video/1", "type": "video", "sizes": {"small": {"w": 385, "h": 680, "resize": "fit"}, "thumb": {"w": 150, "h": 150, "resize": "crop"}, "large": {"w": 480, "h": 848, "resize": "fit"}, "medium": {"w": 480, "h": 848, "resize": "fit"}}, "video_info": {"aspect_ratio": [30, 53], "duration_millis": 23145, "variants": [{"bitrate": 832000, "content_type": "video/mp4", "url": "https://video.twimg.com/ext_tw_video/938942917338640385/pu/vid/362x640/ywNTip2XCSD-BmrD.mp4"}, {"bitrate": 320000, "content_type": "video/mp4", "url": "https://video.twimg.com/ext_tw_video/938942917338640385/pu/vid/180x320/tTd8gJ3fk-QzpT6p.mp4"}, {"content_type": "application/x-mpegURL", "url": "https://video.twimg.com/ext_tw_video/938942917338640385/pu/pl/4j23QL7CECbBcfj0.m3u8"}]}}]}, "extended_entities": {"media": [{"id": 938942917338640385, "id_str": "938942917338640385", "indices": [138, 161], "media_url": "http://pbs.twimg.com/ext_tw_video_thumb/938942917338640385/pu/img/IcidzuFgcfqt8ciT.jpg", "media_url_https": "https://pbs.twimg.com/ext_tw_video_thumb/938942917338640385/pu/img/IcidzuFgcfqt8ciT.jpg", "url": "https://t.co/YHbv1vXSFx", "display_url": "pic.twitter.com/YHbv1vXSFx", "expanded_url": "https://twitter.com/Armaniiarc/status/938950319530299393/video/1", "type": "video", "sizes": {"small": {"w": 385, "h": 680, "resize": "fit"}, "thumb": {"w": 150, "h": 150, "resize": "crop"}, "large": {"w": 480, "h": 848, "resize": "fit"}, "medium": {"w": 480, "h": 848, "resize": "fit"}}, "video_info": {"aspect_ratio": [30, 53], "duration_millis": 23145, "variants": [{"bitrate": 832000, "content_type": "video/mp4", "url": "https://video.twimg.com/ext_tw_video/938942917338640385/pu/vid/362x640/ywNTip2XCSD-BmrD.mp4"}, {"bitrate": 320000, "content_type": "video/mp4", "url": "https://video.twimg.com/ext_tw_video/938942917338640385/pu/vid/180x320/tTd8gJ3fk-QzpT6p.mp4"}, {"content_type": "application/x-mpegURL", "url": "https://video.twimg.com/ext_tw_video/938942917338640385/pu/pl/4j23QL7CECbBcfj0.m3u8"}]}}]}}, "quote_count": 0, "reply_count": 0, "retweet_count": 0, "favorite_count": 0, "entities": {"hashtags": [{"text": "Jam", "indices": [12, 16]}, {"text": "Mellanby", "indices": [61, 70]}, {"text": "UI", "indices": [71, 74]}, {"text": "myhallweek", "indices": [76, 87]}, {"text": "BallondOr", "indices": [88, 98]}], "urls": [{"url": "https://t.co/XCnHNJRVvX", "expanded_url": "https://twitter.com/i/web/status/938950319530299393", "display_url": "twitter.com/i/web/status/9\u2026", "indices": [109, 132]}], "user_mentions": [], "symbols": []}, "favorited": false, "retweeted": false, "possibly_sensitive": false, "filter_level": "low", "lang": "en", "timestamp_ms": "1512698175686"}