{"created_at": "Fri Dec 08 02:03:40 +0000 2017", "id": 938952187140390912, "id_str": "938952187140390912", "text": "RT @ChampionsLeague: Ronaldo and Messi: a decade of domination...\n\n\ud83c\udfc6 2008 - Ronaldo\n\ud83c\udfc6 2009 - Messi\n\ud83c\udfc6 2010 - Messi\n\ud83c\udfc6 2011 - Messi\n\ud83c\udfc6 2012\u2026 ", "source": "<a href=\"http://twitter.com/download/iphone\" rel=\"nofollow\">Twitter for iPhone</a>", "truncated": false, "in_reply_to_status_id": null, "in_reply_to_status_id_str": null, "in_reply_to_user_id": null, "in_reply_to_user_id_str": null, "in_reply_to_screen_name": null, "user": {"id": 516944286, "id_str": "516944286", "name": "Jaynee", "screen_name": "Itsxianhere", "location": "Hogwarts School of W&W", "url": null, "description": "The way you live your life is what decides your life.", "translator_type": "none", "protected": false, "verified": false, "followers_count": 252, "friends_count": 274, "listed_count": 6, "favourites_count": 5316, "statuses_count": 22260, "created_at": "Tue Mar 06 22:14:52 +0000 2012", "utc_offset": 28800, "time_zone": "Kuala Lumpur", "geo_enabled": true, "lang": "en", "contributors_enabled": false, "is_translator": false, "profile_background_color": "312D8A", "profile_background_image_url": "http://pbs.twimg.com/profile_background_images/730644632/e08db0544122d3149f3667449ba99ebd.jpeg", "profile_background_image_url_https": "https://pbs.twimg.com/profile_background_images/730644632/e08db0544122d3149f3667449ba99ebd.jpeg", "profile_background_tile": true, "profile_link_color": "2600FF", "profile_sidebar_border_color": "000000", "profile_sidebar_fill_color": "DDEEF6", "profile_text_color": "333333", "profile_use_background_image": true, "profile_image_url": "http://pbs.twimg.com/profile_images/725409791405756418/zQuU2Fr4_normal.jpg", "profile_image_url_https": "https://pbs.twimg.com/profile_images/725409791405756418/zQuU2Fr4_normal.jpg", "profile_banner_url": "https://pbs.twimg.com/profile_banners/516944286/1424361293", "default_profile": false, "default_profile_image": false, "following": null, "follow_request_sent": null, "notifications": null}, "geo": null, "coordinates": null, "place": null, "contributors": null, "retweeted_status": {"created_at": "Thu Dec 07 19:20:42 +0000 2017", "id": 938850776012787712, "id_str": "938850776012787712", "text": "Ronaldo and Messi: a decade of domination...\n\n\ud83c\udfc6 2008 - Ronaldo\n\ud83c\udfc6 2009 - Messi\n\ud83c\udfc6 2010 - Messi\n\ud83c\udfc6 2011 - Messi\n\ud83c\udfc6 2012\u2026 https://t.co/gHML457jlM", "display_text_range": [0, 140], "source": "<a href=\"http://twitter.com\" rel=\"nofollow\">Twitter Web Client</a>", "truncated": true, "in_reply_to_status_id": null, "in_reply_to_status_id_str": null, "in_reply_to_user_id": null, "in_reply_to_user_id_str": null, "in_reply_to_screen_name": null, "user": {"id": 627673190, "id_str": "627673190", "name": "\u2605 #TeamOfTheYear \u2605", "screen_name": "ChampionsLeague", "location": "Nyon, Vaud", "url": "http://bit.ly/TeamOfTheYear17", "description": "The official home of the #UCL on Twitter. Spanish: @LigadeCampeones U19: @UEFAYouthLeague YouTube: http://uefa.tv", "translator_type": "none", "protected": false, "verified": true, "followers_count": 19289272, "friends_count": 510, "listed_count": 17349, "favourites_count": 1120, "statuses_count": 52633, "created_at": "Thu Jul 05 19:43:40 +0000 2012", "utc_offset": 3600, "time_zone": "Amsterdam", "geo_enabled": false, "lang": "en", "contributors_enabled": false, "is_translator": false, "profile_background_color": "022330", "profile_background_image_url": "http://pbs.twimg.com/profile_background_images/616679637687648258/trkDBuou.jpg", "profile_background_image_url_https": "https://pbs.twimg.com/profile_background_images/616679637687648258/trkDBuou.jpg", "profile_background_tile": false, "profile_link_color": "3B94D9", "profile_sidebar_border_color": "FFFFFF", "profile_sidebar_fill_color": "DDEEF6", "profile_text_color": "333333", "profile_use_background_image": true, "profile_image_url": "http://pbs.twimg.com/profile_images/616969183948054528/mF1Oxcly_normal.jpg", "profile_image_url_https": "https://pbs.twimg.com/profile_images/616969183948054528/mF1Oxcly_normal.jpg", "profile_banner_url": "https://pbs.twimg.com/profile_banners/627673190/1511788202", "default_profile": false, "default_profile_image": false, "following": null, "follow_request_sent": null, "notifications": null}, "geo": null, "coordinates": null, "place": null, "contributors": null, "is_quote_status": false, "extended_tweet": {"full_text": "Ronaldo and Messi: a decade of domination...\n\n\ud83c\udfc6 2008 - Ronaldo\n\ud83c\udfc6 2009 - Messi\n\ud83c\udfc6 2010 - Messi\n\ud83c\udfc6 2011 - Messi\n\ud83c\udfc6 2012 - Messi\n\ud83c\udfc6 2013 - Ronaldo\n\ud83c\udfc6 2014 - Ronaldo\n\ud83c\udfc6 2015 - Messi\n\ud83c\udfc6 2016 - Ronaldo\n\ud83c\udfc6 2017 - Ronaldo\n\n#BallondOr https://t.co/LfXiyVIX0u", "display_text_range": [0, 217], "entities": {"hashtags": [{"text": "BallondOr", "indices": [207, 217]}], "urls": [], "user_mentions": [], "symbols": [], "media": [{"id": 938850339171852291, "id_str": "938850339171852291", "indices": [218, 241], "media_url": "http://pbs.twimg.com/media/DQd3aMOX4AMe9c-.jpg", "media_url_https": "https://pbs.twimg.com/media/DQd3aMOX4AMe9c-.jpg", "url": "https://t.co/LfXiyVIX0u", "display_url": "pic.twitter.com/LfXiyVIX0u", "expanded_url": "https://twitter.com/ChampionsLeague/status/938850776012787712/photo/1", "type": "photo", "sizes": {"large": {"w": 2048, "h": 1365, "resize": "fit"}, "medium": {"w": 1200, "h": 800, "resize": "fit"}, "thumb": {"w": 150, "h": 150, "resize": "crop"}, "small": {"w": 680, "h": 453, "resize": "fit"}}}]}, "extended_entities": {"media": [{"id": 938850339171852291, "id_str": "938850339171852291", "indices": [218, 241], "media_url": "http://pbs.twimg.com/media/DQd3aMOX4AMe9c-.jpg", "media_url_https": "https://pbs.twimg.com/media/DQd3aMOX4AMe9c-.jpg", "url": "https://t.co/LfXiyVIX0u", "display_url": "pic.twitter.com/LfXiyVIX0u", "expanded_url": "https://twitter.com/ChampionsLeague/status/938850776012787712/photo/1", "type": "photo", "sizes": {"large": {"w": 2048, "h": 1365, "resize": "fit"}, "medium": {"w": 1200, "h": 800, "resize": "fit"}, "thumb": {"w": 150, "h": 150, "resize": "crop"}, "small": {"w": 680, "h": 453, "resize": "fit"}}}]}}, "quote_count": 456, "reply_count": 248, "retweet_count": 5990, "favorite_count": 12340, "entities": {"hashtags": [], "urls": [{"url": "https://t.co/gHML457jlM", "expanded_url": "https://twitter.com/i/web/status/938850776012787712", "display_url": "twitter.com/i/web/status/9\u2026", "indices": [116, 139]}], "user_mentions": [], "symbols": []}, "favorited": false, "retweeted": false, "possibly_sensitive": false, "filter_level": "low", "lang": "it"}, "is_quote_status": false, "quote_count": 0, "reply_count": 0, "retweet_count": 8367, "favorite_count": 0, "entities": {"hashtags": [], "urls": [], "user_mentions": [{"screen_name": "ChampionsLeague", "name": "\u2605 #TeamOfTheYear \u2605", "id": 627673190, "id_str": "627673190", "indices": [3, 19]}], "symbols": []}, "favorited": false, "retweeted": false, "filter_level": "low", "lang": "it", "timestamp_ms": "1512698620959"}